oauth_token_manager.py
oauth_token_manager-0.1.1.dist-info/DESCRIPTION.rst
oauth_token_manager-0.1.1.dist-info/METADATA
oauth_token_manager-0.1.1.dist-info/RECORD
oauth_token_manager-0.1.1.dist-info/WHEEL
oauth_token_manager-0.1.1.dist-info/metadata.json
oauth_token_manager-0.1.1.dist-info/top_level.txt
