Metadata-Version: 2.0
Name: oauth-token-manager
Version: 0.1.1
Summary: OAuth 2.0 token manager
Home-page: https://github.com/4Catalyzer/oauth-token-manager
Author: Jimmy Jia
Author-email: tesrin@gmail.com
License: MIT
Keywords: oauth token
Platform: UNKNOWN
Classifier: Development Status :: 3 - Alpha
Classifier: Environment :: Web Environment
Classifier: Intended Audience :: Developers
Classifier: License :: OSI Approved :: MIT License
Classifier: Operating System :: OS Independent
Classifier: Programming Language :: Python
Classifier: Programming Language :: Python :: 3
Classifier: Topic :: Software Development :: Libraries :: Python Modules
Requires-Python: >=3
Requires-Dist: requests
